{
    "Ar36": {
        "error": 0.0006859836123119093, 
        "filter_outliers": true, 
        "filter_outliers_dict": {
            "filter_outliers": true, 
            "iterations": 1, 
            "std_devs": 2
        }, 
        "fit": "Parabolic", 
        "fn": 113, 
        "include_baseline_error": false, 
        "iterations": 1, 
        "n": 120, 
        "std_devs": 2, 
        "value": 0.03397885004323224
    }, 
    "Ar37": {
        "error": 0.00930652431048973, 
        "filter_outliers": true, 
        "filter_outliers_dict": {
            "filter_outliers": true, 
            "iterations": 1, 
            "std_devs": 2
        }, 
        "fit": "Linear", 
        "fn": 116, 
        "include_baseline_error": false, 
        "iterations": 1, 
        "n": 120, 
        "std_devs": 2, 
        "value": 1.4378599710661053
    }, 
    "Ar38": {
        "error": 0.0063124006694738255, 
        "filter_outliers": true, 
        "filter_outliers_dict": {
            "filter_outliers": true, 
            "iterations": 1, 
            "std_devs": 2
        }, 
        "fit": "Linear", 
        "fn": 116, 
        "include_baseline_error": false, 
        "iterations": 1, 
        "n": 120, 
        "std_devs": 2, 
        "value": 3.913083779406143
    }, 
    "Ar39": {
        "error": 0.057173335684315416, 
        "filter_outliers": true, 
        "filter_outliers_dict": {
            "filter_outliers": true, 
            "iterations": 1, 
            "std_devs": 2
        }, 
        "fit": "Parabolic", 
        "fn": 114, 
        "include_baseline_error": false, 
        "iterations": 1, 
        "n": 120, 
        "std_devs": 2, 
        "value": 305.65641008148543
    }, 
    "Ar40": {
        "error": 0.13990238768484553, 
        "filter_outliers": true, 
        "filter_outliers_dict": {
            "filter_outliers": true, 
            "iterations": 1, 
            "std_devs": 2
        }, 
        "fit": "Parabolic", 
        "fn": 113, 
        "include_baseline_error": false, 
        "iterations": 1, 
        "n": 120, 
        "std_devs": 2, 
        "value": 1587.901841000294
    }, 
    "Ar41": {
        "error": 0.004605470634986134, 
        "filter_outliers": true, 
        "filter_outliers_dict": {
            "filter_outliers": true, 
            "iterations": 1, 
            "std_devs": 2
        }, 
        "fit": "Average", 
        "fn": 115, 
        "include_baseline_error": false, 
        "iterations": 1, 
        "n": 120, 
        "std_devs": 2, 
        "value": 0.28567495799582937
    }, 
    "reviewed": true
}