{
    "Ar36": {
        "error": 0.00073132071539835,
        "filter_outliers": true,
        "filter_outliers_dict": {
            "filter_outliers": true,
            "iterations": 1,
            "std_devs": 2
        },
        "fit": "Parabolic",
        "fn": 384,
        "include_baseline_error": false,
        "iterations": 1,
        "n": 400,
        "reviewed": true,
        "std_devs": 2,
        "value": 0.18184147180630866
    },
    "Ar37": {
        "error": 0.004614376157451607,
        "filter_outliers": true,
        "filter_outliers_dict": {
            "filter_outliers": true,
            "iterations": 1,
            "std_devs": 2
        },
        "fit": "Linear",
        "fn": 378,
        "include_baseline_error": false,
        "iterations": 1,
        "n": 400,
        "reviewed": true,
        "std_devs": 2,
        "value": 0.15630825180432673
    },
    "Ar38": {
        "error": 0.0020935905245243612,
        "filter_outliers": true,
        "filter_outliers_dict": {
            "filter_outliers": true,
            "iterations": 1,
            "std_devs": 2
        },
        "fit": "Linear",
        "fn": 379,
        "include_baseline_error": false,
        "iterations": 1,
        "n": 400,
        "reviewed": true,
        "std_devs": 2,
        "value": 0.026560455913746187
    },
    "Ar39": {
        "error": 0.00840786498602844,
        "filter_outliers": true,
        "filter_outliers_dict": {
            "filter_outliers": true,
            "iterations": 1,
            "std_devs": 2
        },
        "fit": "Parabolic",
        "fn": 383,
        "include_baseline_error": false,
        "iterations": 1,
        "n": 400,
        "reviewed": true,
        "std_devs": 2,
        "value": 0.06920122128346623
    },
    "Ar40": {
        "error": 0.01178104396515384,
        "filter_outliers": true,
        "filter_outliers_dict": {
            "filter_outliers": true,
            "iterations": 1,
            "std_devs": 2
        },
        "fit": "Parabolic",
        "fn": 384,
        "include_baseline_error": false,
        "iterations": 1,
        "n": 400,
        "reviewed": true,
        "std_devs": 2,
        "value": 53.53090535138558
    },
    "Ar41": {
        "error": 0.0024923863630829917,
        "filter_outliers": true,
        "filter_outliers_dict": {
            "filter_outliers": true,
            "iterations": 1,
            "std_devs": 2
        },
        "fit": "Average",
        "fn": 382,
        "include_baseline_error": false,
        "iterations": 1,
        "n": 400,
        "std_devs": 2,
        "value": 0.07859470799482422
    },
    "reviewed": true
}