{
    "Ar36": {
        "error": 0.0001269228511570229,
        "filter_outliers": true,
        "filter_outliers_dict": {
            "filter_outliers": true,
            "iterations": 1,
            "std_devs": 2
        },
        "fit": "Parabolic",
        "fn": 374,
        "include_baseline_error": false,
        "iterations": 1,
        "n": 400,
        "reviewed": true,
        "std_devs": 2,
        "value": 0.0019316010516229293
    },
    "Ar37": {
        "error": 0.004949499662608764,
        "filter_outliers": true,
        "filter_outliers_dict": {
            "filter_outliers": true,
            "iterations": 1,
            "std_devs": 2
        },
        "fit": "Linear",
        "fn": 386,
        "include_baseline_error": false,
        "iterations": 1,
        "n": 400,
        "reviewed": true,
        "std_devs": 2,
        "value": 0.15691010903051622
    },
    "Ar38": {
        "error": 0.002600714768768897,
        "filter_outliers": true,
        "filter_outliers_dict": {
            "filter_outliers": true,
            "iterations": 1,
            "std_devs": 2
        },
        "fit": "Linear",
        "fn": 394,
        "include_baseline_error": false,
        "iterations": 1,
        "n": 400,
        "reviewed": true,
        "std_devs": 2,
        "value": -0.006733686698128563
    },
    "Ar39": {
        "error": 0.008427953057887863,
        "filter_outliers": true,
        "filter_outliers_dict": {
            "filter_outliers": true,
            "iterations": 1,
            "std_devs": 2
        },
        "fit": "Parabolic",
        "fn": 382,
        "include_baseline_error": false,
        "iterations": 1,
        "n": 400,
        "reviewed": true,
        "std_devs": 2,
        "value": 0.05040917107794811
    },
    "Ar40": {
        "error": 0.007218336023326637,
        "filter_outliers": true,
        "filter_outliers_dict": {
            "filter_outliers": true,
            "iterations": 1,
            "std_devs": 2
        },
        "fit": "Parabolic",
        "fn": 387,
        "include_baseline_error": false,
        "iterations": 1,
        "n": 400,
        "reviewed": true,
        "std_devs": 2,
        "value": 0.4016002103680423
    },
    "Ar41": {
        "error": 0.002603654714161509,
        "filter_outliers": true,
        "filter_outliers_dict": {
            "filter_outliers": true,
            "iterations": 1,
            "std_devs": 2
        },
        "fit": "Average",
        "fn": 382,
        "include_baseline_error": false,
        "iterations": 1,
        "n": 400,
        "std_devs": 2,
        "value": 0.07179806112977359
    },
    "reviewed": true
}